encrypted_credentials/__init__.py
encrypted_credentials/django_credentials.py
encrypted_credentials/encrypted_file.py
encrypted_credentials-0.0.4.dist-info/LICENSE
encrypted_credentials-0.0.4.dist-info/METADATA
encrypted_credentials-0.0.4.dist-info/WHEEL
encrypted_credentials-0.0.4.dist-info/top_level.txt
encrypted_credentials-0.0.4.dist-info/RECORD
