Metadata-Version: 2.1
Name: encrypted-credentials
Version: 0.0.4
Summary: Encrypt credentials/Django settings to store in repositories
Home-page: https://github.com/jonesim/encrypted-credentials
Author: Ian Jones
License: UNKNOWN
Platform: UNKNOWN
Classifier: Programming Language :: Python :: 3
Classifier: License :: OSI Approved :: MIT License
Classifier: Operating System :: OS Independent
Requires-Python: >=3.6
Requires-Dist: cryptography
